Metadata-Version: 1.0
Name: distribution-probs
Version: 0.1
Summary: Gaussian and Binomial distributions
Home-page: UNKNOWN
Author: David Ukwen
Author-email: ukwendavid@gmail.com
License: UNKNOWN
Platform: UNKNOWN
